Metadata-Version: 2.1
Name: odoo-addon-l10n_br_cnpj_search
Version: 18.0.1.0.1
Requires-Python: >=3.10
Requires-Dist: erpbrasil.base
Requires-Dist: odoo-addon-l10n_br_fiscal==18.0.*
Requires-Dist: odoo-addon-l10n_br_zip==18.0.*
Requires-Dist: odoo==18.0.*
Summary: =?utf-8?q?Integra=C3=A7=C3=A3o_com_os_Webservices_da_ReceitaWS_e_SerPro?=
Home-page: https://github.com/OCA/l10n-brazil
License: AGPL-3
Author: KMEE,Odoo Community Association (OCA)
Author-email: support@odoo-community.org
Classifier: Programming Language :: Python
Classifier: Framework :: Odoo
Classifier: Framework :: Odoo :: 18.0
Classifier: License :: OSI Approved :: GNU Affero General Public License v3
Classifier: Development Status :: 5 - Production/Stable
